taccjm/SSHClient2FA.py
taccjm/TACCJobManager.py
taccjm/__init__.py
taccjm/constants.py
taccjm/exceptions.py
taccjm/taccjm_client.py
taccjm/taccjm_server.py
taccjm/taccjm_server_heartbeat.py
taccjm/utils.py
taccjm/cli/__init__.py
taccjm/cli/cli.py
taccjm/cli/apps/__init__.py
taccjm/cli/apps/app_commands.py
taccjm/cli/files/__init__.py
taccjm/cli/files/file_commands.py
taccjm/cli/jobs/__init__.py
taccjm/cli/jobs/job_commands.py
taccjm/cli/scripts/__init__.py
taccjm/cli/scripts/script_commands.py
taccjm-0.0.4.dist-info/AUTHORS.rst
taccjm-0.0.4.dist-info/LICENSE.txt
taccjm-0.0.4.dist-info/METADATA
taccjm-0.0.4.dist-info/WHEEL
taccjm-0.0.4.dist-info/entry_points.txt
taccjm-0.0.4.dist-info/top_level.txt
taccjm-0.0.4.dist-info/RECORD
