Metadata-Version: 2.1
Name: taccjm
Version: 0.0.4
Summary: TACC Job Manager
Home-page: https://github.com/cdelcastillo21/taccjm/
Author: Carlos del-Castillo-Negrete
Author-email: cdelcastillo21@gmail.com
License: MIT
Project-URL: Source, https://github.com/cdelcastillo21/taccjm/
Project-URL: Tracker, https://github.com/cdelcastillo21/taccjm/issues
Platform: any
Classifier: Development Status :: 4 - Beta
Classifier: Programming Language :: Python
Requires-Python: >3
License-File: LICENSE.txt
License-File: AUTHORS.rst
Requires-Dist: begins (>=0.9)
Requires-Dist: hug (>=2.6.1)
Requires-Dist: paramiko (>=2.7.2)
Requires-Dist: jinja2 (>=3.0.1)
Requires-Dist: psutil (>=5.8.0)
Requires-Dist: numpy (>=1.21.2)
Requires-Dist: prettytable
Requires-Dist: click
Requires-Dist: python-json-logger
Requires-Dist: importlib-metadata ; python_version < "3.8"
Provides-Extra: testing
Requires-Dist: setuptools ; extra == 'testing'
Requires-Dist: pytest ; extra == 'testing'
Requires-Dist: pytest-cov ; extra == 'testing'
Requires-Dist: dotenv ; extra == 'testing'
